{
   "Scalabrino": {
      "identifiers_words_average": "Identifiers words Average",
      "identifiers_words_minimum": "Identifiers words Minimum",
      "abstractness_words_average": "Abstractness words Average",
      "abstractness_words_maximum": "Abstractness words Maximum",
      "abstractness_words_minimum": "Abstractness words Minimum",
      "commented_words_average": "Commented words Average",
      "commented_words_maximum": "Commented words Maximum",
      "synonym_commented_words_average": "Synonym commented words Average",
      "synonym_commented_words_maximum": "Synonym commented words Maximum",
      "expression_complexity_average": "Expression complexity Average",
      "expression_complexity_maximum": "Expression complexity Maximum",
      "expression_complexity_minimum": "Expression complexity Minimum",
      "method_chains_average": "Method chains Average",
      "method_chains_maximum": "Method chains Maximum",
      "method_chains_minimum": "Method chains Minimum",
      "comments_readability": "Comments readability",
      "number_of_senses_average": "Number of senses Average",
      "number_of_senses_maximum": "Number of senses Maximum",
      "semantic_text_coherence_standard": "Semantic Text Coherence Standard",
      "semantic_text_coherence_normalized": "Semantic Text Coherence Normalized",
      "text_coherence_average": "Text Coherence Average",
      "text_coherence_minimum": "Text Coherence Minimum",
      "text_coherence_maximum": "Text Coherence Maximum",
      "readability": "Readability"
   },
   "BW": {
      "assignment_average": "Assignment Average",
      "blank_lines_average": "blank lines Average",
      "commas_average": "commas Average",
      "comments_average": "comments Average",
      "comparisons_average": "comparisons Average",
      "identifiers_length_average": "Identifiers Length Average",
      "conditionals_average": "conditionals Average",
      "indentation_average": "indentation Average",
      "keywords_average": "keywords Average",
      "line_length_average": "line length Average",
      "loops_average": "loops Average",
      "number_of_identifiers_average": "number of identifiers Average",
      "numbers_average": "numbers Average",
      "operators_average": "operators Average",
      "parenthesis_average": "parenthesis Average",
      "periods_average": "periods Average",
      "spaces_average": "spaces Average",
      "identifiers_length_maximum": "Identifiers Length Maximum",
      "indentation_maximum": "indentation Maximum",
      "keywords_maximum": "keywords Maximum",
      "line_length_maximum": "line length Maximum",
      "number_of_identifiers_maximum": "number of identifiers Maximum",
      "numbers_maximum": "numbers Maximum",
      "char_maximum": "char Maximum",
      "words_maximum": "words Maximum"
   },
   "Posnett": {
      "entropy": "entropy",
      "volume": "volume",
      "lines": "lines"
   },
   "Dorn": {
      "dft_assignments": "DFT Assignments",
      "dft_commas": "DFT Commas",
      "dft_comments": "DFT Comments",
      "dft_comparisons": "DFT Comparisons",
      "dft_conditionals": "DFT Conditionals",
      "dft_indentations": "DFT Indentations",
      "dft_keywords": "DFT Keywords",
      "dft_linelengths": "DFT LineLengths",
      "dft_loops": "DFT Loops",
      "dft_identifiers": "DFT Identifiers",
      "dft_numbers": "DFT Numbers",
      "dft_operators": "DFT Operators",
      "dft_parenthesis": "DFT Parenthesis",
      "dft_periods": "DFT Periods",
      "dft_spaces": "DFT Spaces",
      "comments_x": "Comments X",
      "comments_y": "Comments Y",
      "identifiers_x": "Identifiers X",
      "identifiers_y": "Identifiers Y",
      "keywords_x": "Keywords X",
      "keywords_y": "Keywords Y",
      "numbers_x": "Numbers X",
      "numbers_y": "Numbers Y",
      "strings_x": "Strings X",
      "strings_y": "Strings Y",
      "literals_x": "Literals X",
      "literals_y": "Literals Y",
      "operators_x": "Operators X",
      "operators_y": "Operators Y",
      "areas_comments": "Areas Comments",
      "areas_identifiers": "Areas Identifiers",
      "areas_keywords": "Areas Keywords",
      "areas_numbers": "Areas Numbers",
      "areas_strings": "Areas Strings",
      "areas_literals": "Areas Literals",
      "areas_operators": "Areas Operators",
      "areas_identifiers_comments": "Areas Identifiers/Comments",
      "areas_keywords_comments": "Areas Keywords/Comments",
      "areas_numbers_comments": "Areas Numbers/Comments",
      "areas_strings_comments": "Areas Strings/Comments",
      "areas_literals_comments": "Areas Literals/Comments",
      "areas_operators_comments": "Areas Operators/Comments",
      "areas_keywords_identifiers": "Areas Keywords/Identifiers",
      "areas_numbers_identifiers": "Areas Numbers/Identifiers",
      "areas_strings_identifiers": "Areas Strings/Identifiers",
      "areas_literals_identifiers": "Areas Literals/Identifiers",
      "areas_operators_identifiers": "Areas Operators/Identifiers",
      "areas_numbers_keywords": "Areas Numbers/Keywords",
      "areas_strings_keywords": "Areas Strings/Keywords",
      "areas_literals_keywords": "Areas Literals/Keywords",
      "areas_operators_keywords": "Areas Operators/Keywords",
      "areas_strings_numbers": "Areas Strings/Numbers",
      "areas_literals_numbers": "Areas Literals/Numbers",
      "areas_operators_numbers": "Areas Operators/Numbers",
      "areas_literals_strings": "Areas Literals/Strings",
      "areas_operators_strings": "Areas Operators/Strings",
      "areas_operators_literals": "Areas Operators/Literals",
      "align_blocks": "align blocks",
      "align_extent": "align extent"
   }
}